Универ/5 курс/APCU/APCU_Lab2_Memory/src/lpm_ram_io_model.vhd
library ieee;
use ieee.std_logic_1164.all;
use ieee.numeric_std.all;

entity lpm_ram_io_model is
  port (
    clk_i     : in    std_logic;
    address_i : in    std_logic_vector(3 downto 0);
    we_i      : in    std_logic;
    out_en_i  : in    std_logic;
    data_io   : inout std_logic_vector(7 downto 0);
    q_dbg_o   : out   std_logic_vector(7 downto 0)
  );
end entity;

architecture rtl of lpm_ram_io_model is
  type memory_t is array (0 to 15) of std_logic_vector(7 downto 0);
  signal ram : memory_t := (others => (others => '0'));
  signal q_reg : std_logic_vector(7 downto 0) := (others => 'Z');
begin
  process(clk_i)
  begin
    if rising_edge(clk_i) then
      if we_i = '1' then
        ram(to_integer(unsigned(address_i))) <= data_io;
      end if;

      if out_en_i = '1' and we_i = '0' then
        q_reg <= ram(to_integer(unsigned(address_i)));
      else
        q_reg <= (others => 'Z');
      end if;
    end if;
  end process;

  data_io <= q_reg when out_en_i = '1' and we_i = '0' else (others => 'Z');
  q_dbg_o <= q_reg;
end architecture;

Универ/5 курс/APCU/APCU_Lab2_Memory/src/lpm_rom_model.vhd
library ieee;
use ieee.std_logic_1164.all;
use ieee.numeric_std.all;

entity lpm_rom_model is
  port (
    clk_i     : in  std_logic;
    address_i : in  std_logic_vector(3 downto 0);
    memenab_i : in  std_logic;
    q_o       : out std_logic_vector(7 downto 0)
  );
end entity;

architecture rtl of lpm_rom_model is
  type memory_t is array (0 to 15) of std_logic_vector(7 downto 0);
  signal q_reg : std_logic_vector(7 downto 0) := (others => 'Z');

  constant ROM_C : memory_t := (
    0  => x"11",
    1  => x"27",
    2  => x"3C",
    3  => x"45",
    4  => x"5A",
    5  => x"6E",
    6  => x"73",
    7  => x"8F",
    8  => x"91",
    9  => x"A4",
    10 => x"B8",
    11 => x"C2",
    12 => x"D5",
    13 => x"E9",
    14 => x"F0",
    15 => x"0D"
  );
begin
  process(clk_i)
  begin
    if rising_edge(clk_i) then
      if memenab_i = '1' then
        q_reg <= ROM_C(to_integer(unsigned(address_i)));
      else
        q_reg <= (others => 'Z');
      end if;
    end if;
  end process;

  q_o <= q_reg;
end architecture;

Универ/5 курс/APCU/APCU_Lab2_Memory/src/memory_transfer.vhd
library ieee;
use ieee.std_logic_1164.all;
use ieee.numeric_std.all;

entity memory_transfer is
  port (
    clk_i       : in  std_logic;
    rst_i       : in  std_logic;
    start_i     : in  std_logic;
    done_o      : out std_logic;
    busy_o      : out std_logic;
    verify_ok_o : out std_logic;
    state_o     : out std_logic_vector(2 downto 0);
    data_bus_o  : out std_logic_vector(7 downto 0);
    rom_q_o     : out std_logic_vector(7 downto 0);
    reg_q_o     : out std_logic_vector(7 downto 0);
    ram_q_o     : out std_logic_vector(7 downto 0);
    rom_addr_o  : out std_logic_vector(3 downto 0);
    ram_addr_o  : out std_logic_vector(3 downto 0)
  );
end entity;

architecture rtl of memory_transfer is
  constant SRC_ADDR_C  : std_logic_vector(3 downto 0) := x"4";
  constant DST_ADDR_C  : std_logic_vector(3 downto 0) := x"5";
  constant EXPECTED_C  : std_logic_vector(7 downto 0) := x"5A";

  type state_t is (S_IDLE, S_READ_ROM, S_LOAD_REG, S_WRITE_RAM, S_READ_RAM, S_DONE);

  signal state_reg : state_t := S_IDLE;
  signal state_next : state_t;
  signal data_bus : std_logic_vector(7 downto 0);
  signal rom_q : std_logic_vector(7 downto 0);
  signal ram_q : std_logic_vector(7 downto 0);
  signal reg_q : std_logic_vector(7 downto 0) := (others => '0');

  signal rom_en : std_logic;
  signal reg_oe : std_logic;
  signal ram_we : std_logic;
  signal ram_oe : std_logic;
begin
  U_ROM : entity work.lpm_rom_model
    port map (
      clk_i     => clk_i,
      address_i => SRC_ADDR_C,
      memenab_i => rom_en,
      q_o       => rom_q
    );

  U_RAM : entity work.lpm_ram_io_model
    port map (
      clk_i     => clk_i,
      address_i => DST_ADDR_C,
      we_i      => ram_we,
      out_en_i  => ram_oe,
      data_io   => data_bus,
      q_dbg_o   => ram_q
    );

  data_bus <= rom_q when rom_en = '1' else (others => 'Z');
  data_bus <= reg_q when reg_oe = '1' else (others => 'Z');

  process(state_reg, start_i)
  begin
    state_next <= state_reg;
    case state_reg is
      when S_IDLE =>
        if start_i = '1' then
          state_next <= S_READ_ROM;
        end if;
      when S_READ_ROM =>
        state_next <= S_LOAD_REG;
      when S_LOAD_REG =>
        state_next <= S_WRITE_RAM;
      when S_WRITE_RAM =>
        state_next <= S_READ_RAM;
      when S_READ_RAM =>
        state_next <= S_DONE;
      when S_DONE =>
        if start_i = '0' then
          state_next <= S_IDLE;
        end if;
    end case;
  end process;

  process(clk_i)
  begin
    if rising_edge(clk_i) then
      if rst_i = '1' then
        state_reg <= S_IDLE;
        reg_q <= (others => '0');
      else
        if state_reg = S_LOAD_REG then
          reg_q <= data_bus;
        end if;
        state_reg <= state_next;
      end if;
    end if;
  end process;

  rom_en <= '1' when state_reg = S_READ_ROM or state_reg = S_LOAD_REG else '0';
  reg_oe <= '1' when state_reg = S_WRITE_RAM else '0';
  ram_we <= '1' when state_reg = S_WRITE_RAM else '0';
  ram_oe <= '1' when state_reg = S_READ_RAM or state_reg = S_DONE else '0';

  done_o      <= '1' when state_reg = S_DONE else '0';
  busy_o      <= '0' when state_reg = S_IDLE or state_reg = S_DONE else '1';
  verify_ok_o <= '1' when state_reg = S_DONE and ram_q = EXPECTED_C else '0';

  with state_reg select state_o <=
    "000" when S_IDLE,
    "001" when S_READ_ROM,
    "010" when S_LOAD_REG,
    "011" when S_WRITE_RAM,
    "100" when S_READ_RAM,
    "101" when others;

  data_bus_o <= data_bus;
  rom_q_o    <= rom_q;
  reg_q_o    <= reg_q;
  ram_q_o    <= ram_q;
  rom_addr_o <= SRC_ADDR_C;
  ram_addr_o <= DST_ADDR_C;
end architecture;

Универ/5 курс/APCU/APCU_Lab2_Memory/tb/tb_memory_transfer.vhd
library ieee;
use ieee.std_logic_1164.all;
use ieee.numeric_std.all;

entity tb_memory_transfer is
end entity;

architecture sim of tb_memory_transfer is
  signal clk       : std_logic := '0';
  signal rst       : std_logic := '1';
  signal start     : std_logic := '0';
  signal done      : std_logic;
  signal busy      : std_logic;
  signal verify_ok : std_logic;
  signal state     : std_logic_vector(2 downto 0);
  signal data_bus  : std_logic_vector(7 downto 0);
  signal rom_q     : std_logic_vector(7 downto 0);
  signal reg_q     : std_logic_vector(7 downto 0);
  signal ram_q     : std_logic_vector(7 downto 0);
  signal rom_addr  : std_logic_vector(3 downto 0);
  signal ram_addr  : std_logic_vector(3 downto 0);

  procedure tick(signal clk_s : in std_logic) is
  begin
    wait until rising_edge(clk_s);
    wait for 1 ns;
  end procedure;
begin
  clk <= not clk after 5 ns;

  DUT : entity work.memory_transfer
    port map (
      clk_i       => clk,
      rst_i       => rst,
      start_i     => start,
      done_o      => done,
      busy_o      => busy,
      verify_ok_o => verify_ok,
      state_o     => state,
      data_bus_o  => data_bus,
      rom_q_o     => rom_q,
      reg_q_o     => reg_q,
      ram_q_o     => ram_q,
      rom_addr_o  => rom_addr,
      ram_addr_o  => ram_addr
    );

  stimulus : process
  begin
    tick(clk);
    rst <= '0';
    start <= '1';

    tick(clk);
    assert state = "001" report "FSM must enter ROM read state" severity failure;
    assert rom_addr = x"4" report "ROM source address must be 4" severity failure;

    tick(clk);
    assert state = "010" report "FSM must enter register load state" severity failure;
    assert data_bus = x"5A" report "Register must see ROM[4] value 0x5A on shared bus" severity failure;

    tick(clk);
    assert state = "011" report "FSM must enter RAM write state" severity failure;
    assert reg_q = x"5A" report "Register must capture value 0x5A" severity failure;
    assert ram_addr = x"5" report "RAM destination address must be 5" severity failure;
    assert data_bus = x"5A" report "Register must drive value 0x5A during RAM write" severity failure;

    tick(clk);
    assert state = "100" report "FSM must enter RAM readback state" severity failure;

    tick(clk);
    assert done = '1' report "Transfer must finish with done=1" severity failure;
    assert verify_ok = '1' report "Verification flag must be active after successful transfer" severity failure;
    assert ram_q = x"5A" report "RAM[5] must contain transferred value 0x5A" severity failure;
    assert data_bus = x"5A" report "RAM readback must drive 0x5A onto the bus" severity failure;

    start <= '0';
    tick(clk);
    assert done = '0' report "FSM must return to idle after start is released" severity failure;

    assert false report "tb_memory_transfer: TEST PASSED" severity note;
    wait;
  end process;
end architecture;

Универ/5 курс/APCU/APCU_Lab2_Memory/sim/memory_transfer.vcd
$date
  Tue Jun  9 12:31:23 2026
$end
$version
  GHDL v0
$end
$timescale
  1 fs
$end
$scope module standard $end
$upscope $end
$scope module textio $end
$upscope $end
$scope module std_logic_1164 $end
$upscope $end
$scope module numeric_std $end
$upscope $end
$scope module tb_memory_transfer $end
$var reg 1 ! clk $end
$var reg 1 " rst $end
$var reg 1 # start $end
$var reg 1 $ done $end
$var reg 1 % busy $end
$var reg 1 & verify_ok $end
$var reg 3 ' state[2:0] $end
$var reg 8 ( data_bus[7:0] $end
$var reg 8 ) rom_q[7:0] $end
$var reg 8 * reg_q[7:0] $end
$var reg 8 + ram_q[7:0] $end
$var reg 4 , rom_addr[3:0] $end
$var reg 4 - ram_addr[3:0] $end
$scope module dut $end
$var reg 1 . clk_i $end
$var reg 1 / rst_i $end
$var reg 1 0 start_i $end
$var reg 1 1 done_o $end
$var reg 1 2 busy_o $end
$var reg 1 3 verify_ok_o $end
$var reg 3 4 state_o[2:0] $end
$var reg 8 5 data_bus_o[7:0] $end
$var reg 8 6 rom_q_o[7:0] $end
$var reg 8 7 reg_q_o[7:0] $end
$var reg 8 8 ram_q_o[7:0] $end
$var reg 4 9 rom_addr_o[3:0] $end
$var reg 4 : ram_addr_o[3:0] $end
$comment state_reg is not handled $end
$comment state_next is not handled $end
$var reg 8 ; data_bus[7:0] $end
$var reg 8 < rom_q[7:0] $end
$var reg 8 = ram_q[7:0] $end
$var reg 8 > reg_q[7:0] $end
$var reg 1 ? rom_en $end
$var reg 1 @ reg_oe $end
$var reg 1 A ram_we $end
$var reg 1 B ram_oe $end
$scope module u_rom $end
$var reg 1 C clk_i $end
$var reg 4 D address_i[3:0] $end
$var reg 1 E memenab_i $end
$var reg 8 F q_o[7:0] $end
$var reg 8 G q_reg[7:0] $end
$upscope $end
$scope module u_ram $end
$var reg 1 H clk_i $end
$var reg 4 I address_i[3:0] $end
$var reg 1 J we_i $end
$var reg 1 K out_en_i $end
$var reg 8 L data_io[7:0] $end
$var reg 8 M q_dbg_o[7:0] $end
$comment ram is not handled $end
$var reg 8 N q_reg[7:0] $end
$upscope $end
$upscope $end
$upscope $end
$enddefinitions $end
#0
0!
1"
0#
0$
0%
0&
b000 '
bZZZZZZZZ (
bZZZZZZZZ )
b00000000 *
bZZZZZZZZ +
b0100 ,
b0101 -
0.
1/
00
01
02
03
b000 4
bZZZZZZZZ 5
bZZZZZZZZ 6
b00000000 7
bZZZZZZZZ 8
b0100 9
b0101 :
bZZZZZZZZ ;
bZZZZZZZZ <
bZZZZZZZZ =
b00000000 >
0?
0@
0A
0B
0C
b0100 D
0E
bZZZZZZZZ F
bZZZZZZZZ G
0H
b0101 I
0J
0K
bZZZZZZZZ L
bZZZZZZZZ M
bZZZZZZZZ N
#5000000
1!
1.
1C
1H
#6000000
0"
1#
0/
10
#10000000
0!
0.
0C
0H
#15000000
1!
1%
b001 '
1.
12
b001 4
1?
1C
1E
1H
#20000000
0!
0.
0C
0H
#25000000
1!
b010 '
b01011010 (
b01011010 )
1.
b010 4
b01011010 5
b01011010 6
b01011010 ;
b01011010 <
1C
b01011010 F
b01011010 G
1H
b01011010 L
#30000000
0!
0.
0C
0H
#35000000
1!
b011 '
b01011010 *
1.
b011 4
b01011010 7
b01011010 >
0?
1@
1A
1C
0E
1H
1J
#40000000
0!
0.
0C
0H
#45000000
1!
b100 '
bZZZZZZZZ (
bZZZZZZZZ )
1.
b100 4
bZZZZZZZZ 5
bZZZZZZZZ 6
bZZZZZZZZ ;
bZZZZZZZZ <
0@
0A
1B
1C
bZZZZZZZZ F
bZZZZZZZZ G
1H
0J
1K
bZZZZZZZZ L
#50000000
0!
0.
0C
0H
#55000000
1!
1$
0%
1&
b101 '
b01011010 (
b01011010 +
1.
11
02
13
b101 4
b01011010 5
b01011010 8
b01011010 ;
b01011010 =
1C
1H
b01011010 L
b01011010 M
b01011010 N
#56000000
0#
00
#60000000
0!
0.
0C
0H
#65000000
1!
0$
0&
b000 '
bZZZZZZZZ (
1.
01
03
b000 4
bZZZZZZZZ 5
bZZZZZZZZ ;
0B
1C
1H
0K
bZZZZZZZZ L
#70000000
0!
0.
0C
0H
#75000000
1!
bZZZZZZZZ +
1.
bZZZZZZZZ 8
bZZZZZZZZ =
1C
1H
bZZZZZZZZ M
bZZZZZZZZ N
