Универ/5 курс/APCU/APCU_Lab1_Counter/src/mod11_counter.vhd
library ieee;
use ieee.std_logic_1164.all;
use ieee.numeric_std.all;

entity mod11_counter is
  port (
    clk_i  : in  std_logic;
    rst_i  : in  std_logic;
    en_i   : in  std_logic;
    load_i : in  std_logic;
    q_o    : out std_logic_vector(3 downto 0);
    tc_o   : out std_logic
  );
end entity;

architecture rtl of mod11_counter is
  constant COUNT_MIN_C : unsigned(3 downto 0) := to_unsigned(5, 4);
  constant COUNT_MAX_C : unsigned(3 downto 0) := to_unsigned(15, 4);

  signal count_reg : unsigned(3 downto 0) := COUNT_MIN_C;
begin
  process(clk_i)
  begin
    if rising_edge(clk_i) then
      if rst_i = '1' or load_i = '1' then
        count_reg <= COUNT_MIN_C;
      elsif en_i = '1' then
        if count_reg = COUNT_MAX_C then
          count_reg <= COUNT_MIN_C;
        else
          count_reg <= count_reg + 1;
        end if;
      end if;
    end if;
  end process;

  q_o  <= std_logic_vector(count_reg);
  tc_o <= '1' when count_reg = COUNT_MAX_C and en_i = '1' else '0';
end architecture;

Универ/5 курс/APCU/APCU_Lab1_Counter/tb/tb_mod11_counter.vhd
library ieee;
use ieee.std_logic_1164.all;
use ieee.numeric_std.all;

entity tb_mod11_counter is
end entity;

architecture sim of tb_mod11_counter is
  signal clk  : std_logic := '0';
  signal rst  : std_logic := '1';
  signal en   : std_logic := '0';
  signal load : std_logic := '0';
  signal q    : std_logic_vector(3 downto 0);
  signal tc   : std_logic;

  procedure tick(signal clk_s : in std_logic) is
  begin
    wait until rising_edge(clk_s);
    wait for 1 ns;
  end procedure;

  procedure expect_q(
    constant expected : in natural;
    constant message  : in string
  ) is
  begin
    assert unsigned(q) = to_unsigned(expected, 4)
      report message severity failure;
  end procedure;
begin
  clk <= not clk after 5 ns;

  DUT : entity work.mod11_counter
    port map (
      clk_i  => clk,
      rst_i  => rst,
      en_i   => en,
      load_i => load,
      q_o    => q,
      tc_o   => tc
    );

  stimulus : process
  begin
    tick(clk);
    expect_q(5, "Reset must force initial state 5");

    rst <= '0';
    en <= '1';

    for expected in 6 to 15 loop
      tick(clk);
      expect_q(expected, "Counter sequence from 5 to 15 is broken");
    end loop;

    assert tc = '1'
      report "Terminal-count flag must be active at value 15 while enable is high"
      severity failure;

    tick(clk);
    expect_q(5, "Counter must wrap from 15 to 5");

    en <= '0';
    tick(clk);
    tick(clk);
    expect_q(5, "Counter must hold its state when enable is low");

    load <= '1';
    en <= '1';
    tick(clk);
    expect_q(5, "Load must force state 5");

    load <= '0';
    tick(clk);
    expect_q(6, "Counter must continue after load is released");

    assert false report "tb_mod11_counter: TEST PASSED" severity note;
    wait;
  end process;
end architecture;

Универ/5 курс/APCU/APCU_Lab1_Counter/sim/mod11_counter.vcd
$date
  Tue Jun  9 11:35:44 2026
$end
$version
  GHDL v0
$end
$timescale
  1 fs
$end
$scope module standard $end
$upscope $end
$scope module textio $end
$upscope $end
$scope module std_logic_1164 $end
$upscope $end
$scope module numeric_std $end
$upscope $end
$scope module tb_mod11_counter $end
$var reg 1 ! clk $end
$var reg 1 " rst $end
$var reg 1 # en $end
$var reg 1 $ load $end
$var reg 4 % q[3:0] $end
$var reg 1 & tc $end
$scope module dut $end
$var reg 1 ' clk_i $end
$var reg 1 ( rst_i $end
$var reg 1 ) en_i $end
$var reg 1 * load_i $end
$var reg 4 + q_o[3:0] $end
$var reg 1 , tc_o $end
$var reg 4 - count_reg[3:0] $end
$upscope $end
$upscope $end
$enddefinitions $end
#0
0!
1"
0#
0$
b0101 %
0&
0'
1(
0)
0*
b0101 +
0,
b0101 -
#5000000
1!
1'
#6000000
0"
1#
0(
1)
#10000000
0!
0'
#15000000
1!
b0110 %
1'
b0110 +
b0110 -
#20000000
0!
0'
#25000000
1!
b0111 %
1'
b0111 +
b0111 -
#30000000
0!
0'
#35000000
1!
b1000 %
1'
b1000 +
b1000 -
#40000000
0!
0'
#45000000
1!
b1001 %
1'
b1001 +
b1001 -
#50000000
0!
0'
#55000000
1!
b1010 %
1'
b1010 +
b1010 -
#60000000
0!
0'
#65000000
1!
b1011 %
1'
b1011 +
b1011 -
#70000000
0!
0'
#75000000
1!
b1100 %
1'
b1100 +
b1100 -
#80000000
0!
0'
#85000000
1!
b1101 %
1'
b1101 +
b1101 -
#90000000
0!
0'
#95000000
1!
b1110 %
1'
b1110 +
b1110 -
#100000000
0!
0'
#105000000
1!
b1111 %
1&
1'
b1111 +
1,
b1111 -
#110000000
0!
0'
#115000000
1!
b0101 %
0&
1'
b0101 +
0,
b0101 -
#116000000
0#
0)
#120000000
0!
0'
#125000000
1!
1'
#130000000
0!
0'
#135000000
1!
1'
#136000000
1#
1$
1)
1*
#140000000
0!
0'
#145000000
1!
1'
#146000000
0$
0*
#150000000
0!
0'
#155000000
1!
b0110 %
1'
b0110 +
b0110 -
#160000000
0!
0'
#165000000
1!
b0111 %
1'
b0111 +
b0111 -
#170000000
0!
0'
#175000000
1!
b1000 %
1'
b1000 +
b1000 -
