Универ/5 курс/APCU/APCU_Lab3_SN74145/src/sn74145_sequential.vhd
library ieee;
use ieee.std_logic_1164.all;

entity sn74145_sequential is
  port (
    a_i : in  std_logic;
    b_i : in  std_logic;
    c_i : in  std_logic;
    d_i : in  std_logic;
    y_o : out std_logic_vector(9 downto 0)
  );
end entity;

architecture rtl of sn74145_sequential is
begin
  process(a_i, b_i, c_i, d_i)
    variable sel_v : std_logic_vector(3 downto 0);
    variable y_v   : std_logic_vector(9 downto 0);
  begin
    sel_v := d_i & c_i & b_i & a_i;
    y_v := (others => '1');

    case sel_v is
      when "0000" => y_v(0) := '0';
      when "0001" => y_v(1) := '0';
      when "0010" => y_v(2) := '0';
      when "0011" => y_v(3) := '0';
      when "0100" => y_v(4) := '0';
      when "0101" => y_v(5) := '0';
      when "0110" => y_v(6) := '0';
      when "0111" => y_v(7) := '0';
      when "1000" => y_v(8) := '0';
      when "1001" => y_v(9) := '0';
      when others => null;
    end case;

    y_o <= y_v;
  end process;
end architecture;

Универ/5 курс/APCU/APCU_Lab3_SN74145/src/sn74145_concurrent.vhd
library ieee;
use ieee.std_logic_1164.all;

entity sn74145_concurrent is
  port (
    a_i : in  std_logic;
    b_i : in  std_logic;
    c_i : in  std_logic;
    d_i : in  std_logic;
    y_o : out std_logic_vector(9 downto 0)
  );
end entity;

architecture rtl of sn74145_concurrent is
begin
  y_o(0) <= a_i or b_i or c_i or d_i;
  y_o(1) <= (not a_i) or b_i or c_i or d_i;
  y_o(2) <= a_i or (not b_i) or c_i or d_i;
  y_o(3) <= (not a_i) or (not b_i) or c_i or d_i;
  y_o(4) <= a_i or b_i or (not c_i) or d_i;
  y_o(5) <= (not a_i) or b_i or (not c_i) or d_i;
  y_o(6) <= a_i or (not b_i) or (not c_i) or d_i;
  y_o(7) <= (not a_i) or (not b_i) or (not c_i) or d_i;
  y_o(8) <= a_i or b_i or c_i or (not d_i);
  y_o(9) <= (not a_i) or b_i or c_i or (not d_i);
end architecture;

Универ/5 курс/APCU/APCU_Lab3_SN74145/tb/tb_sn74145.vhd
library ieee;
use ieee.std_logic_1164.all;
use ieee.numeric_std.all;

entity tb_sn74145 is
end entity;

architecture sim of tb_sn74145 is
  signal a       : std_logic := '0';
  signal b       : std_logic := '0';
  signal c       : std_logic := '0';
  signal d       : std_logic := '0';
  signal y_logic : std_logic_vector(9 downto 0);
  signal y_seq   : std_logic_vector(9 downto 0);

  function bit_from_int(value_i : integer) return std_logic is
  begin
    if value_i = 0 then
      return '0';
    end if;
    return '1';
  end function;
begin
  U_LOGIC : entity work.sn74145_concurrent
    port map (
      a_i => a,
      b_i => b,
      c_i => c,
      d_i => d,
      y_o => y_logic
    );

  U_SEQ : entity work.sn74145_sequential
    port map (
      a_i => a,
      b_i => b,
      c_i => c,
      d_i => d,
      y_o => y_seq
    );

  stimulus : process
    variable expected_v : std_logic_vector(9 downto 0);
  begin
    for code_i in 0 to 15 loop
      a <= bit_from_int(code_i mod 2);
      b <= bit_from_int((code_i / 2) mod 2);
      c <= bit_from_int((code_i / 4) mod 2);
      d <= bit_from_int((code_i / 8) mod 2);
      wait for 10 ns;

      expected_v := (others => '1');
      if code_i <= 9 then
        expected_v(code_i) := '0';
      end if;

      assert y_logic = expected_v
        report "Concurrent decoder output mismatch" severity failure;
      assert y_seq = expected_v
        report "Sequential decoder output mismatch" severity failure;
      assert y_logic = y_seq
        report "Concurrent and sequential implementations are not equivalent" severity failure;
    end loop;

    assert false report "tb_sn74145: TEST PASSED; checked 16 BCD/input combinations" severity note;
    wait;
  end process;
end architecture;

Универ/5 курс/APCU/APCU_Lab3_SN74145/sim/sn74145.vcd
$date
  Tue Jun  9 18:03:12 2026
$end
$version
  GHDL v0
$end
$timescale
  1 fs
$end
$scope module standard $end
$upscope $end
$scope module textio $end
$upscope $end
$scope module std_logic_1164 $end
$upscope $end
$scope module numeric_std $end
$upscope $end
$scope module tb_sn74145 $end
$var reg 1 ! a $end
$var reg 1 " b $end
$var reg 1 # c $end
$var reg 1 $ d $end
$var reg 10 % y_logic[9:0] $end
$var reg 10 & y_seq[9:0] $end
$scope module u_logic $end
$var reg 1 ' a_i $end
$var reg 1 ( b_i $end
$var reg 1 ) c_i $end
$var reg 1 * d_i $end
$var reg 10 + y_o[9:0] $end
$upscope $end
$scope module u_seq $end
$var reg 1 , a_i $end
$var reg 1 - b_i $end
$var reg 1 . c_i $end
$var reg 1 / d_i $end
$var reg 10 0 y_o[9:0] $end
$upscope $end
$upscope $end
$enddefinitions $end
#0
0!
0"
0#
0$
b1111111110 %
b1111111110 &
0'
0(
0)
0*
b1111111110 +
0,
0-
0.
0/
b1111111110 0
#10000000
1!
b1111111101 %
b1111111101 &
1'
b1111111101 +
1,
b1111111101 0
#20000000
0!
1"
b1111111011 %
b1111111011 &
0'
1(
b1111111011 +
0,
1-
b1111111011 0
#30000000
1!
b1111110111 %
b1111110111 &
1'
b1111110111 +
1,
b1111110111 0
#40000000
0!
0"
1#
b1111101111 %
b1111101111 &
0'
0(
1)
b1111101111 +
0,
0-
1.
b1111101111 0
#50000000
1!
b1111011111 %
b1111011111 &
1'
b1111011111 +
1,
b1111011111 0
#60000000
0!
1"
b1110111111 %
b1110111111 &
0'
1(
b1110111111 +
0,
1-
b1110111111 0
#70000000
1!
b1101111111 %
b1101111111 &
1'
b1101111111 +
1,
b1101111111 0
#80000000
0!
0"
0#
1$
b1011111111 %
b1011111111 &
0'
0(
0)
1*
b1011111111 +
0,
0-
0.
1/
b1011111111 0
#90000000
1!
b0111111111 %
b0111111111 &
1'
b0111111111 +
1,
b0111111111 0
#100000000
0!
1"
b1111111111 %
b1111111111 &
0'
1(
b1111111111 +
0,
1-
b1111111111 0
#110000000
1!
1'
1,
#120000000
0!
0"
1#
0'
0(
1)
0,
0-
1.
#130000000
1!
1'
1,
#140000000
0!
1"
0'
1(
0,
1-
#150000000
1!
1'
1,
